Classes/ECE3401/lab0.vhd
-- Simulation Tutorial
-- 1-bit Adder

-- This is just to make a reference to some common things needed.
LIBRARY IEEE;
use IEEE.STD_LOGIC_1164.ALL;
use IEEE.NUMERIC_STD.ALL;

-- We declare the 1-bit adder with the inputs and outputs
-- shown inside the port().
-- This will add two bits together(x,y), with a carry in(cin) and 
-- output the sum(sum) and a carry out(cout).
entity BIT_ADDER is
        port( a, b, cin         : in  unsigned(0 downto 0);
              sum, cout         : out STD_LOGIC );
end BIT_ADDER;

-- This describes the functionality of the 1-BIT adder.
architecture BHV of BIT_ADDER is
signal temp : unsigned(1 downto 0); -- 'signal' refers to an internal bus
begin
        -- Calculate the complete sum.
		temp <= ('0' & a) + ('0' & b) + ('0' & cin); -- '&' concatenates 2 values.
		
		-- Sum of the 1-BIT adder.
        sum <=  temp(0);

        -- Carry out of the 1-BIT adder.
        cout <= temp(1);
end BHV;

Classes/ECE3401/test0.vhd
-- 1-bit Adder Testbench

-- A testbench is used to functionally test a digital design.
-- The output of the testbench should allow the designer to see if
-- the design worked.  The testbench should also report where the testbench
-- failed.

-- This is just to make a reference to some common things needed.
LIBRARY IEEE;
use IEEE.STD_LOGIC_1164.ALL;
use IEEE.NUMERIC_STD.ALL;

-- Decare a testbench.  Notice that the testbench does not have any
-- input or output ports.
entity TEST_ADD is
end TEST_ADD;

-- Describes the functionality of the tesbench.
architecture TEST of TEST_ADD is 

	-- The object that we wish to test is declared as a component of 
	-- the test bench. Its functionality has already been described elsewhere.
	-- This simply describes what the object's inputs and outputs are, it
	-- does not actually create the object.
	component BIT_ADDER 
		port( a, b, cin         : in  unsigned;
	      	sum, cout         : out STD_LOGIC );
	end component;

	-- Specifies which description of the adder you will use.
	for U1: BIT_ADDER use entity WORK.BIT_ADDER(BHV);

	-- Create a set of signals which will be associated with both the inputs
	-- and outputs of the component that we wish to test.
	signal A, B	: unsigned(0 downto 0);
	signal CIN	: unsigned (0 downto 0);
	signal SUM	: STD_LOGIC;
	signal COUT	: STD_LOGIC;

	-- This is where the testbench for the BIT_ADDER actually begins.	
	begin
	
	-- Create a 1-bit adder in the testbench. 	
	-- The signals specified above are mapped to their appropriate
	-- roles in the 1-bit adder which we have created.
	U1: BIT_ADDER port map (A, B, CIN, SUM, COUT);
	
	-- The process is where the actual testing is done.
	process
	begin

		-- We are now going to set the inputs of the adder and test
		-- the outputs to verify the functionality of our 1-bit adder.

		-- Case 0 : 0+0 with carry in of 0.

		-- Set the signals for the inputs.
		A <= to_unsigned(0,1);
		B <= to_unsigned(0,1);
		CIN <= to_unsigned(0,1);
		
		-- Wait a short amount of time and then check to see if the 
		-- outputs are what they should be. If not, then report an error
		-- so that we will know there is a problem.
		wait for 10 ns;
		assert ( SUM = '0'  ) report "Failed Case 0 - SUM" severity error;
		assert ( COUT = '0' ) report "Failed Case 0 - COUT" severity error;
		wait for 40 ns;

		-- Carry out the same process outlined above for the other 7 cases.

		-- Case 1 : 0+0 with carry in of 1.
		A <= to_unsigned(0,1);
		B <= to_unsigned(0,1);
		CIN <= to_unsigned(1,1);
		wait for 10 ns;
		assert ( SUM = '1'  ) report "Failed Case 1 - SUM" severity error;
		assert ( COUT = '0' ) report "Failed Case 1 - COUT" severity error;
		report "A: " & integer'image(to_integer(A));
		report "B: " & integer'image(to_integer(B));
		report "CIN: " & integer'image(to_integer(CIN));
		report "SUM: " & std_logic'image(SUM);
		report "COUT: " & std_logic'image(COUT);
		report "--------- ";
		wait for 40 ns;

		-- Case 2 : 0+1 with carry in of 0.
		A <= to_unsigned(0,1);
		B <= to_unsigned(1,1);
		CIN <= to_unsigned(0,1);
		wait for 10 ns;
		assert ( SUM = '1'  ) report "Failed Case 2 - SUM" severity error;
		assert ( COUT = '0' ) report "Failed Case 2 - COUT" severity error;
		report "A: " & integer'image(to_integer(A));
		report "B: " & integer'image(to_integer(B));
		report "CIN: " & integer'image(to_integer(CIN));
		report "SUM: " & std_logic'image(SUM);
		report "COUT: " & std_logic'image(COUT);
		report "--------- ";
		wait for 40 ns;

		-- Case 3 : 0+1 with carry in of 1.
		A <= to_unsigned(0,1);
		B <= to_unsigned(1,1);
		CIN <= to_unsigned(1,1);
		wait for 10 ns;
		assert ( SUM = '0'  ) report "Failed Case 3 - SUM" severity error;
		assert ( COUT = '1' ) report "Failed Case 3 - COUT" severity error;
		report "A: " & integer'image(to_integer(A));
		report "B: " & integer'image(to_integer(B));
		report "CIN: " & integer'image(to_integer(CIN));
		report "SUM: " & std_logic'image(SUM);
		report "COUT: " & std_logic'image(COUT);
		report "--------- ";
		wait for 40 ns;

		-- Case 4 : 1+0 with carry in of 0.
		A <= to_unsigned(1,1);
		B <= to_unsigned(0,1);
		CIN <= to_unsigned(0,1);
		wait for 10 ns;
		assert ( SUM = '1'  ) report "Failed Case 4 - SUM" severity error;
		assert ( COUT = '0' ) report "Failed Case 4 - COUT" severity error;
		report "A: " & integer'image(to_integer(A));
		report "B: " & integer'image(to_integer(B));
		report "CIN: " & integer'image(to_integer(CIN));
		report "SUM: " & std_logic'image(SUM);
		report "COUT: " & std_logic'image(COUT);
		report "--------- ";
		wait for 40 ns;

		-- Case 5 : 1+0 with carry in of 1.
		A <= to_unsigned(1,1);
		B <= to_unsigned(0,1);
		CIN <= to_unsigned(1,1);
		wait for 10 ns;
		assert ( SUM = '0'  ) report "Failed Case 5 - SUM" severity error;
		assert ( COUT = '1' ) report "Failed Case 5 - COUT" severity error;
		report "A: " & integer'image(to_integer(A));
		report "B: " & integer'image(to_integer(B));
		report "CIN: " & integer'image(to_integer(CIN));
		report "SUM: " & std_logic'image(SUM);
		report "COUT: " & std_logic'image(COUT);
		report "--------- ";
		wait for 40 ns;

		-- Case 6 : 1+1 with carry in of 0.
		A <= to_unsigned(1,1);
		B <= to_unsigned(1,1);
		CIN <= to_unsigned(0,1);
		wait for 10 ns;
		assert ( SUM = '0'  ) report "Failed Case 6 - SUM" severity error;
		assert ( COUT = '1' ) report "Failed Case 6 - COUT" severity error;
		report "A: " & integer'image(to_integer(A));
		report "B: " & integer'image(to_integer(B));
		report "CIN: " & integer'image(to_integer(CIN));
		report "SUM: " & std_logic'image(SUM);
		report "COUT: " & std_logic'image(COUT);
		report "--------- ";
		wait for 40 ns;

		-- Case 7 : 1+1 with carry in of 1.
		A <= to_unsigned(1,1);
		B <= to_unsigned(1,1);
		CIN <= to_unsigned(1,1);
		wait for 10 ns;
		assert ( SUM = '1'  ) report "Failed Case 7 - SUM" severity error;
		assert ( COUT = '1' ) report "Failed Case 7 - COUT" severity error;
		report "A: " & integer'image(to_integer(A));
		report "B: " & integer'image(to_integer(B));
		report "CIN: " & integer'image(to_integer(CIN));
		report "SUM: " & std_logic'image(SUM);
		report "COUT: " & std_logic'image(COUT);
		report "--------- ";
		wait for 40 ns;

	end process;
END TEST;

Classes/ECE3401/PA0/pa0.vcd
$date
  Fri Jan 30 23:50:43 2026
$end
$version
  GHDL v0
$end
$timescale
  1 fs
$end
$scope module standard $end
$upscope $end
$scope module std_logic_1164 $end
$upscope $end
$scope module numeric_std $end
$upscope $end
$scope module test_add $end
$var reg 1 ! a[0:0] $end
$var reg 1 " b[0:0] $end
$var reg 1 # cin[0:0] $end
$var reg 1 $ sum $end
$var reg 1 % cout $end
$scope module u1 $end
$var reg 1 & a[0:0] $end
$var reg 1 ' b[0:0] $end
$var reg 1 ( cin[0:0] $end
$var reg 1 ) sum $end
$var reg 1 * cout $end
$var reg 2 + temp[1:0] $end
$upscope $end
$upscope $end
$enddefinitions $end
#0
b0 !
b0 "
b0 #
0$
0%
b0 &
b0 '
b0 (
0)
0*
b00 +
#10000000
#50000000
b1 #
1$
b1 (
1)
b01 +
#60000000
#100000000
b1 "
b0 #
b1 '
b0 (
#110000000
#150000000
b1 #
0$
1%
b1 (
0)
1*
b10 +
#160000000
#200000000
b1 !
b0 "
b0 #
1$
0%
b1 &
b0 '
b0 (
1)
0*
b01 +
#210000000
#250000000
b1 #
0$
1%
b1 (
0)
1*
b10 +
#260000000
#300000000
b1 "
b0 #
b1 '
b0 (
#310000000
#350000000
b1 #
1$
b1 (
1)
b11 +
#360000000
#400000000
b0 !
b0 "
b0 #
0$
0%
b0 &
b0 '
b0 (
0)
0*
b00 +
#410000000
#450000000
b1 #
1$
b1 (
1)
b01 +
#460000000
#500000000
b1 "
b0 #
b1 '
b0 (
